{
  "id": "8274cec2-b8ea-45bd-b206-5443269713f0",
  "slug": "/en/monterosso/boat-tours",
  "title": "Boat Tours from Monterosso",
  "page_type": "boat-tours",
  "seo": {
    "title": "Monterosso Boat Tours 2025 | See Cinque Terre from the Sea",
    "description": "Book boat tours from Monterosso. See all five villages from the water, sunset cruises, and swimming excursions.",
    "keywords": ["Monterosso boat tours", "Cinque Terre boat trip", "sunset cruise", "ferry"]
  },
  "body": [
    {
      "type": "hero-section",
      "variant": "simple-centered",
      "eyebrow": "Monterosso al Mare",
      "title": "Boat Tours from Monterosso",
      "subtitle": "See Cinque Terre from its best angle—the sea. Regular ferries, private charters, and sunset wine cruises.",
      "buttons": [
        { "text": "View All Tours", "url": "#list", "variant": "primary" },
        { "text": "Back to Monterosso", "url": "/en/monterosso", "variant": "secondary" }
      ]
    },
    {
      "type": "feature-section",
      "variant": "simple-3x2-grid",
      "eyebrow": "Options",
      "title": "Types of Boat Tours",
      "features": [
        { "icon": "ship", "title": "Ferry Service", "description": "Regular boats between villages. Buy tickets at the port." },
        { "icon": "sunset", "title": "Sunset Cruise", "description": "Evening tours with wine and appetizers. Book ahead!" },
        { "icon": "anchor", "title": "Private Charter", "description": "Your own boat and captain. Flexible itinerary." },
        { "icon": "swim", "title": "Swimming Tour", "description": "Stop at hidden coves for swimming. Bring snorkels!" },
        { "icon": "camera", "title": "Photo Tour", "description": "Best angles of all five villages from the sea." },
        { "icon": "fish", "title": "Fishing Trip", "description": "Traditional fishing experience with local fishermen." }
      ]
    },
    {
      "type": "cta-section",
      "variant": "simple-centered",
      "title": "Explore Monterosso",
      "buttons": [
        { "text": "Beaches", "url": "/en/monterosso/beaches", "variant": "primary" },
        { "text": "Back to Monterosso", "url": "/en/monterosso", "variant": "secondary" }
      ]
    }
  ],
  "metadata": {
    "city": "monterosso",
    "lang": "en",
    "page_type": "boat-tours"
  },
  "status": "published",
  "created_at": "2025-12-04T13:18:46.911Z",
  "updated_at": "2025-12-12T22:00:00.000Z"
}