{
  "id": "f4c2f02c-4a63-4d32-88b6-c007757404d3",
  "slug": "/en/corniglia/overview",
  "title": "Corniglia - The Hidden Gem of Cinque Terre",
  "page_type": "overview",
  "seo": {
    "title": "Corniglia Travel Guide 2025 | The Village Above the Sea",
    "description": "Discover Corniglia, Cinque Terre's hidden gem perched high on cliffs. The only village without direct sea access, reached by the famous 382-step Lardarina staircase, surrounded by vineyards.",
    "keywords": ["Corniglia", "Cinque Terre", "Lardarina steps", "Italian vineyards", "peaceful Italy", "cliff village"]
  },
  "body": [
    {
      "type": "hero-section",
      "variant": "split-with-image",
      "eyebrow": "The Village Above the Sea",
      "title": "Corniglia",
      "subtitle": "Perched 100 meters above the Mediterranean, Corniglia is Cinque Terre's most peaceful village. The only one without direct sea access, reached by climbing the legendary 382-step Lardarina staircase. Surrounded by terraced vineyards producing excellent white wine.",
      "buttons": [
        { "text": "Plan Your Visit", "url": "#visit", "variant": "primary" },
        { "text": "Things to Do", "url": "/en/corniglia/things-to-do", "variant": "secondary" }
      ],
      "image": "https://images.unsplash.com/photo-1516483638261-f4dbaf036963?w=1200&q=80"
    },
    {
      "type": "feature-section",
      "variant": "simple-3x2-grid",
      "eyebrow": "Why Visit Corniglia",
      "title": "Authentic Cinque Terre Experience",
      "subtitle": "Fewer crowds, local atmosphere, stunning panoramic views.",
      "features": [
        {
          "icon": "stairs",
          "title": "The Lardarina Staircase",
          "description": "Famous 382-step brick staircase climbing from the train station to the village. A rite of passage for every visitor."
        },
        {
          "icon": "wine",
          "title": "Ancient Vineyards",
          "description": "Surrounded by terraced vineyards producing Vernaccia white wine. The agricultural heart of Cinque Terre."
        },
        {
          "icon": "peace",
          "title": "Peaceful Atmosphere",
          "description": "Fewest tourists of all five villages. Experience authentic local life away from the crowds."
        },
        {
          "icon": "view",
          "title": "Panoramic Terraces",
          "description": "Breathtaking 360-degree views from the clifftop position. See three other villages from various viewpoints."
        },
        {
          "icon": "hiking",
          "title": "Best Hiking Access",
          "description": "Central position makes it ideal for hiking to other villages. Well-connected to all major trails."
        },
        {
          "icon": "food",
          "title": "Local Cuisine",
          "description": "Traditional trattorias serving local families for generations. Authentic recipes without tourist markup."
        }
      ]
    },
    {
      "type": "cta-section",
      "variant": "simple-centered-with-gradient",
      "title": "Experience the Real Cinque Terre",
      "subtitle": "Climb the Lardarina, taste local wine, and discover why Corniglia rewards those who make the effort.",
      "buttons": [
        { "text": "View Accommodations", "url": "/en/corniglia/hotels", "variant": "primary" },
        { "text": "Hiking Trails", "url": "/en/corniglia/hiking", "variant": "secondary" }
      ]
    }
  ],
  "metadata": {
    "city": "corniglia",
    "lang": "en",
    "page_type": "overview"
  },
  "status": "published",
  "created_at": "2025-12-04T13:18:46.911Z",
  "updated_at": "2025-12-12T22:00:00.000Z"
}
